{"at_report": {"0": {"ra": {"value": "181.696229633333", "error": "0.09", "units": "arcsec"}, "dec": {"value": "69.1303496", "error": "0.09", "units": "arcsec"}, "reporting_group_id": "74", "discovery_data_source_id": "48", "reporter": "F. Forster, F.E. Bauer, G. Pignata, A. Munoz-Arancibia, L. Hernandez-Garcia, L. Galbany, E. Camacho, J. Silva-Farfan, A. Mourao, J. Arredondo, G. Cabrera-Vives, R. Carrasco-Davis, P.A. Estevez, P. Huijse, E. Reyes, I. Reyes, P. Sanchez-Saez, C. Valenzuela, E. Castillo, D. Ruz-Mieres, D. Rodriguez-Mancini, M. Catelan, S. Eyheramendy, M.J. Graham on behalf of the ALeRCE broker", "discovery_datetime": "2021-02-25 09:51:28.999", "at_type": "1", "internal_name": "ZTF21aanncjl", "remarks": "Early SN candidate (g-rise > 0.09+-0.02 mag/day, r-rise > 0.09+-0.01 mag/day) classified using ALeRCE's stamp classifier - see http://arxiv.org/abs/2008.03309 - and the public ZTF stream. Discovery image and light curve in http://alerce.online/object/ZTF21aanncjl ", "non_detection": {"obsdate": "2021-02-09 10:48:08.001", "limiting_flux": "18.7227001190186", "flux_units": "1", "filter_value": "110", "instrument_value": "196", "exptime": "30", "observer": "Robot", "comments": "Data provided by ZTF"}, "photometry": {"photometry_group": {"0": {"obsdate": "2021-02-25 09:51:28.999", "flux": "19.2434005737305", "flux_error": "0.284222006797791", "limiting_flux": "19.1951999664307", "flux_units": "1", "filter_value": "110", "instrument_value": "196", "exptime": "30", "observer": "Robot", "comments": "Data provided by ZTF"}, "1": {"obsdate": "2021-02-27 09:32:25.996", "flux": "19.1320781707764", "flux_error": "0.20883996784687", "limiting_flux": "19.0680274963379", "flux_units": "1", "filter_value": "110", "instrument_value": "196", "exptime": "30", "observer": "Robot", "comments": "Data provided by ZTF"}, "2": {"obsdate": "2021-02-27 10:40:34.003", "flux": "18.8039798736572", "flux_error": "0.201729938387871", "limiting_flux": "19.0861968994141", "flux_units": "1", "filter_value": "111", "instrument_value": "196", "exptime": "30", "observer": "Robot", "comments": "Data provided by ZTF"}}}, "host_name": "SDSS J120646.89+690747.9"}, "1": {"ra": {"value": "90.6019192", "error": "0.09", "units": "arcsec"}, "dec": {"value": "67.78035485", "error": "0.09", "units": "arcsec"}, "reporting_group_id": "74", "discovery_data_source_id": "48", "reporter": "F. Forster, F.E. Bauer, G. Pignata, A. Munoz-Arancibia, L. Hernandez-Garcia, L. Galbany, E. Camacho, J. Silva-Farfan, A. Mourao, J. Arredondo, G. Cabrera-Vives, R. Carrasco-Davis, P.A. Estevez, P. Huijse, E. Reyes, I. Reyes, P. Sanchez-Saez, C. Valenzuela, E. Castillo, D. Ruz-Mieres, D. Rodriguez-Mancini, M. Catelan, S. Eyheramendy, M.J. Graham on behalf of the ALeRCE broker", "discovery_datetime": "2021-02-23 03:57:13.000", "at_type": "1", "internal_name": "ZTF21aanmvvz", "remarks": "Early SN candidate (r-rise > 0.07+-0.01 mag/day) classified using ALeRCE's stamp classifier - see http://arxiv.org/abs/2008.03309 - and the public ZTF stream. Discovery image and light curve in http://alerce.online/object/ZTF21aanmvvz ", "non_detection": {"obsdate": "2021-02-21 05:26:47.003", "limiting_flux": "19.6961002349854", "flux_units": "1", "filter_value": "111", "instrument_value": "196", "exptime": "30", "observer": "Robot", "comments": "Data provided by ZTF"}, "photometry": {"photometry_group": {"0": {"obsdate": "2021-02-23 03:57:13.000", "flux": "20.2763996124268", "flux_error": "0.342750996351242", "limiting_flux": "19.8229007720947", "flux_units": "1", "filter_value": "110", "instrument_value": "196", "exptime": "30", "observer": "Robot", "comments": "Data provided by ZTF"}, "1": {"obsdate": "2021-02-27 05:36:14.003", "flux": "19.6562595367432", "flux_error": "0.191587716341019", "limiting_flux": "19.3189239501953", "flux_units": "1", "filter_value": "111", "instrument_value": "196", "exptime": "30", "observer": "Robot", "comments": "Data provided by ZTF"}}}, "host_name": "WISEA J060224.50+674651.1"}}}