{"at_report": {"0": {"ra": {"value": "221.7865716", "error": "0.085", "units": "arcsec"}, "dec": {"value": "-26.953714", "error": "0.085", "units": "arcsec"}, "reporting_group_id": "74", "discovery_data_source_id": "48", "reporter": "A. Munoz-Arancibia, F. Forster, F.E. Bauer, G. Pignata, A. Mourao, L. Hernandez-Garcia, L. Galbany, R. Hoshino, E. Camacho, J. Silva-Farfan, J. Arredondo, G. Cabrera-Vives, R. Carrasco-Davis, P.A. Estevez, P. Huijse, A. Moya E. Reyes, I. Reyes, P. Sanchez-Saez, D. Rodriguez-Mancini, M. Catelan, S. Eyheramendy, M.J. Graham on behalf of the ALeRCE broker", "discovery_datetime": "2022-04-26 09:39:36.000", "at_type": "1", "internal_name": "ZTF22aahtxfb", "remarks": "Early SN candidate (r-rise > 1.15+-0.10 mag/day) classified using ALeRCE's stamp classifier (Carrasco-Davis et al. 2021) and the public ZTF stream. Discovery image and light curve in http://alerce.online/object/ZTF22aahtxfb ", "non_detection": {"obsdate": "2022-04-26 08:31:16.000", "limiting_flux": "17.5564", "flux_units": "1", "filter_value": "110", "instrument_value": "196", "exptime": "30", "observer": "Robot", "comments": "Data provided by ZTF"}, "photometry": {"photometry_group": {"0": {"obsdate": "2022-04-26 09:39:36.000", "flux": "17.136583", "flux_error": "0.20368443", "limiting_flux": "17.007158", "flux_units": "1", "filter_value": "111", "instrument_value": "196", "exptime": "30", "observer": "Robot", "comments": "Data provided by ZTF"}}}, "host_name": "WISEA J144708.77-265713.3", "host_redshift": "0.067954"}, "1": {"ra": {"value": "222.2418943", "error": "0.085", "units": "arcsec"}, "dec": {"value": "5.5692215", "error": "0.085", "units": "arcsec"}, "reporting_group_id": "74", "discovery_data_source_id": "48", "reporter": "A. Munoz-Arancibia, F. Forster, F.E. Bauer, G. Pignata, A. Mourao, L. Hernandez-Garcia, L. Galbany, R. Hoshino, E. Camacho, J. Silva-Farfan, J. Arredondo, G. Cabrera-Vives, R. Carrasco-Davis, P.A. Estevez, P. Huijse, A. Moya E. Reyes, I. Reyes, P. Sanchez-Saez, D. Rodriguez-Mancini, M. Catelan, S. Eyheramendy, M.J. Graham on behalf of the ALeRCE broker", "discovery_datetime": "2022-04-26 08:53:13.998", "at_type": "1", "internal_name": "ZTF22aahtiah", "remarks": "SN candidate classified using ALeRCE's stamp classifier (Carrasco-Davis et al. 2021) and the public ZTF stream. Discovery image and light curve in http://alerce.online/object/ZTF22aahtiah ", "non_detection": {"obsdate": "2022-04-24 10:04:33.001", "limiting_flux": "20.1579", "flux_units": "1", "filter_value": "110", "instrument_value": "196", "exptime": "30", "observer": "Robot", "comments": "Data provided by ZTF"}, "photometry": {"photometry_group": {"0": {"obsdate": "2022-04-26 08:53:13.998", "flux": "20.313688", "flux_error": "0.2167625", "limiting_flux": "20.64043", "flux_units": "1", "filter_value": "110", "instrument_value": "196", "exptime": "30", "observer": "Robot", "comments": "Data provided by ZTF"}}}, "host_name": "SDSS J144858.02+053409.6"}, "2": {"ra": {"value": "224.9727472", "error": "0.085", "units": "arcsec"}, "dec": {"value": "-1.9347225", "error": "0.085", "units": "arcsec"}, "reporting_group_id": "74", "discovery_data_source_id": "48", "reporter": "A. Munoz-Arancibia, F. Forster, F.E. Bauer, G. Pignata, A. Mourao, L. Hernandez-Garcia, L. Galbany, R. Hoshino, E. Camacho, J. Silva-Farfan, J. Arredondo, G. Cabrera-Vives, R. Carrasco-Davis, P.A. Estevez, P. Huijse, A. Moya E. Reyes, I. Reyes, P. Sanchez-Saez, D. Rodriguez-Mancini, M. Catelan, S. Eyheramendy, M.J. Graham on behalf of the ALeRCE broker", "discovery_datetime": "2022-04-26 08:33:17.997", "at_type": "1", "internal_name": "ZTF22aahtdjt", "remarks": "SN candidate classified using ALeRCE's stamp classifier (Carrasco-Davis et al. 2021) and the public ZTF stream. Discovery image and light curve in http://alerce.online/object/ZTF22aahtdjt ", "non_detection": {"obsdate": "2022-04-21 08:26:44.998", "limiting_flux": "20.1151", "flux_units": "1", "filter_value": "111", "instrument_value": "196", "exptime": "30", "observer": "Robot", "comments": "Data provided by ZTF"}, "photometry": {"photometry_group": {"0": {"obsdate": "2022-04-26 08:33:17.997", "flux": "19.799273", "flux_error": "0.17557456", "limiting_flux": "20.25636", "flux_units": "1", "filter_value": "110", "instrument_value": "196", "exptime": "30", "observer": "Robot", "comments": "Data provided by ZTF"}}}, "host_name": "SDSS J145953.40-015605.6"}, "3": {"ra": {"value": "171.6239414", "error": "0.085", "units": "arcsec"}, "dec": {"value": "-10.6808821", "error": "0.085", "units": "arcsec"}, "reporting_group_id": "74", "discovery_data_source_id": "48", "reporter": "A. Munoz-Arancibia, F. Forster, F.E. Bauer, G. Pignata, A. Mourao, L. Hernandez-Garcia, L. Galbany, R. Hoshino, E. Camacho, J. Silva-Farfan, J. Arredondo, G. Cabrera-Vives, R. Carrasco-Davis, P.A. Estevez, P. Huijse, A. Moya E. Reyes, I. Reyes, P. Sanchez-Saez, D. Rodriguez-Mancini, M. Catelan, S. Eyheramendy, M.J. Graham on behalf of the ALeRCE broker", "discovery_datetime": "2022-04-26 05:33:24.002", "at_type": "1", "internal_name": "ZTF22aahrcfm", "remarks": "Early SN candidate (r-rise > 0.44+-0.10 mag/day) classified using ALeRCE's stamp classifier (Carrasco-Davis et al. 2021) and the public ZTF stream. Discovery image and light curve in http://alerce.online/object/ZTF22aahrcfm ", "non_detection": {"obsdate": "2022-04-24 06:03:18.003", "limiting_flux": "19.7023", "flux_units": "1", "filter_value": "111", "instrument_value": "196", "exptime": "30", "observer": "Robot", "comments": "Data provided by ZTF"}, "photometry": {"photometry_group": {"0": {"obsdate": "2022-04-26 05:33:24.002", "flux": "18.838078", "flux_error": "0.20693956", "limiting_flux": "18.684193", "flux_units": "1", "filter_value": "111", "instrument_value": "196", "exptime": "30", "observer": "Robot", "comments": "Data provided by ZTF"}}}, "host_name": "SDSS J112629.75-104051.2"}, "4": {"ra": {"value": "179.3552377", "error": "0.085", "units": "arcsec"}, "dec": {"value": "-8.9477771", "error": "0.085", "units": "arcsec"}, "reporting_group_id": "74", "discovery_data_source_id": "48", "reporter": "A. Munoz-Arancibia, F. Forster, F.E. Bauer, G. Pignata, A. Mourao, L. Hernandez-Garcia, L. Galbany, R. Hoshino, E. Camacho, J. Silva-Farfan, J. Arredondo, G. Cabrera-Vives, R. Carrasco-Davis, P.A. Estevez, P. Huijse, A. Moya E. Reyes, I. Reyes, P. Sanchez-Saez, D. Rodriguez-Mancini, M. Catelan, S. Eyheramendy, M.J. Graham on behalf of the ALeRCE broker", "discovery_datetime": "2022-04-26 05:34:04.999", "at_type": "1", "internal_name": "ZTF22aahqtvw", "remarks": "Early SN candidate (r-rise > 0.39+-0.09 mag/day) classified using ALeRCE's stamp classifier (Carrasco-Davis et al. 2021) and the public ZTF stream. Discovery image and light curve in http://alerce.online/object/ZTF22aahqtvw ", "non_detection": {"obsdate": "2022-04-24 06:03:59.000", "limiting_flux": "19.9082", "flux_units": "1", "filter_value": "111", "instrument_value": "196", "exptime": "30", "observer": "Robot", "comments": "Data provided by ZTF"}, "photometry": {"photometry_group": {"0": {"obsdate": "2022-04-26 05:34:04.999", "flux": "19.132746", "flux_error": "0.17158961", "limiting_flux": "19.228168", "flux_units": "1", "filter_value": "111", "instrument_value": "196", "exptime": "30", "observer": "Robot", "comments": "Data provided by ZTF"}}}, "host_name": "WISEA J115725.24-085652.1"}, "5": {"ra": {"value": "188.2544765", "error": "0.085", "units": "arcsec"}, "dec": {"value": "1.7453423", "error": "0.085", "units": "arcsec"}, "reporting_group_id": "74", "discovery_data_source_id": "48", "reporter": "A. Munoz-Arancibia, F. Forster, F.E. Bauer, G. Pignata, A. Mourao, L. Hernandez-Garcia, L. Galbany, R. Hoshino, E. Camacho, J. Silva-Farfan, J. Arredondo, G. Cabrera-Vives, R. Carrasco-Davis, P.A. Estevez, P. Huijse, A. Moya E. Reyes, I. Reyes, P. Sanchez-Saez, D. Rodriguez-Mancini, M. Catelan, S. Eyheramendy, M.J. Graham on behalf of the ALeRCE broker", "discovery_datetime": "2022-04-26 05:35:25.999", "at_type": "1", "internal_name": "ZTF22aahqtmf", "remarks": "Early SN candidate (r-rise > 0.66+-0.08 mag/day) classified using ALeRCE's stamp classifier (Carrasco-Davis et al. 2021) and the public ZTF stream. Discovery image and light curve in http://alerce.online/object/ZTF22aahqtmf ", "non_detection": {"obsdate": "2022-04-24 06:54:36.996", "limiting_flux": "19.8172", "flux_units": "1", "filter_value": "111", "instrument_value": "196", "exptime": "30", "observer": "Robot", "comments": "Data provided by ZTF"}, "photometry": {"photometry_group": {"0": {"obsdate": "2022-04-26 05:35:25.999", "flux": "18.538239", "flux_error": "0.16310947", "limiting_flux": "18.738115", "flux_units": "1", "filter_value": "111", "instrument_value": "196", "exptime": "30", "observer": "Robot", "comments": "Data provided by ZTF"}}}, "host_name": "WISEA J123301.05+014443.1", "host_redshift": "0.074504"}, "6": {"ra": {"value": "179.4300626", "error": "0.085", "units": "arcsec"}, "dec": {"value": "-12.5954242", "error": "0.085", "units": "arcsec"}, "reporting_group_id": "74", "discovery_data_source_id": "48", "reporter": "A. Munoz-Arancibia, F. Forster, F.E. Bauer, G. Pignata, A. Mourao, L. Hernandez-Garcia, L. Galbany, R. Hoshino, E. Camacho, J. Silva-Farfan, J. Arredondo, G. Cabrera-Vives, R. Carrasco-Davis, P.A. Estevez, P. Huijse, A. Moya E. Reyes, I. Reyes, P. Sanchez-Saez, D. Rodriguez-Mancini, M. Catelan, S. Eyheramendy, M.J. Graham on behalf of the ALeRCE broker", "discovery_datetime": "2022-04-26 05:34:04.999", "at_type": "1", "internal_name": "ZTF22aahqpbl", "remarks": "Early SN candidate (r-rise > 0.35+-0.10 mag/day) classified using ALeRCE's stamp classifier (Carrasco-Davis et al. 2021) and the public ZTF stream. Discovery image and light curve in http://alerce.online/object/ZTF22aahqpbl ", "non_detection": {"obsdate": "2022-04-24 06:03:59.000", "limiting_flux": "19.7767", "flux_units": "1", "filter_value": "111", "instrument_value": "196", "exptime": "30", "observer": "Robot", "comments": "Data provided by ZTF"}, "photometry": {"photometry_group": {"0": {"obsdate": "2022-04-26 05:34:04.999", "flux": "19.076887", "flux_error": "0.2049518", "limiting_flux": "19.335827", "flux_units": "1", "filter_value": "111", "instrument_value": "196", "exptime": "30", "observer": "Robot", "comments": "Data provided by ZTF"}}}, "host_name": "LCRS B115509.7-121901"}, "7": {"ra": {"value": "149.04860765", "error": "0.085", "units": "arcsec"}, "dec": {"value": "-20.79374045", "error": "0.085", "units": "arcsec"}, "reporting_group_id": "74", "discovery_data_source_id": "48", "reporter": "A. Munoz-Arancibia, F. Forster, F.E. Bauer, G. Pignata, A. Mourao, L. Hernandez-Garcia, L. Galbany, R. Hoshino, E. Camacho, J. Silva-Farfan, J. Arredondo, G. Cabrera-Vives, R. Carrasco-Davis, P.A. Estevez, P. Huijse, A. Moya E. Reyes, I. Reyes, P. Sanchez-Saez, D. Rodriguez-Mancini, M. Catelan, S. Eyheramendy, M.J. Graham on behalf of the ALeRCE broker", "discovery_datetime": "2022-04-24 04:32:28.997", "at_type": "1", "internal_name": "ZTF22aahqbki", "remarks": "SN candidate classified using ALeRCE's stamp classifier (Carrasco-Davis et al. 2021) and the public ZTF stream. Discovery image and light curve in http://alerce.online/object/ZTF22aahqbki ", "non_detection": {"obsdate": "2022-04-20 04:02:56.000", "limiting_flux": "19.3492", "flux_units": "1", "filter_value": "111", "instrument_value": "196", "exptime": "30", "observer": "Robot", "comments": "Data provided by ZTF"}, "photometry": {"photometry_group": {"0": {"obsdate": "2022-04-24 04:32:28.997", "flux": "19.4199", "flux_error": "0.223174", "limiting_flux": "19.3664", "flux_units": "1", "filter_value": "111", "instrument_value": "196", "exptime": "30", "observer": "Robot", "comments": "Data provided by ZTF"}, "1": {"obsdate": "2022-04-24 05:11:49.998", "flux": "19.6856", "flux_error": "0.330068", "limiting_flux": "19.4486", "flux_units": "1", "filter_value": "110", "instrument_value": "196", "exptime": "30", "observer": "Robot", "comments": "Data provided by ZTF"}, "2": {"obsdate": "2022-04-26 04:03:40.997", "flux": "19.4034", "flux_error": "0.244981", "limiting_flux": "19.7703", "flux_units": "1", "filter_value": "110", "instrument_value": "196", "exptime": "30", "observer": "Robot", "comments": "Data provided by ZTF"}, "3": {"obsdate": "2022-04-26 05:13:35.000", "flux": "19.390362", "flux_error": "0.18986905", "limiting_flux": "19.661577", "flux_units": "1", "filter_value": "111", "instrument_value": "196", "exptime": "30", "observer": "Robot", "comments": "Data provided by ZTF"}}}, "host_name": "WISEA J095611.38-204738.0"}, "8": {"ra": {"value": "159.2790101", "error": "0.085", "units": "arcsec"}, "dec": {"value": "-16.5660459", "error": "0.085", "units": "arcsec"}, "reporting_group_id": "74", "discovery_data_source_id": "48", "reporter": "A. Munoz-Arancibia, F. Forster, F.E. Bauer, G. Pignata, A. Mourao, L. Hernandez-Garcia, L. Galbany, R. Hoshino, E. Camacho, J. Silva-Farfan, J. Arredondo, G. Cabrera-Vives, R. Carrasco-Davis, P.A. Estevez, P. Huijse, A. Moya E. Reyes, I. Reyes, P. Sanchez-Saez, D. Rodriguez-Mancini, M. Catelan, S. Eyheramendy, M.J. Graham on behalf of the ALeRCE broker", "discovery_datetime": "2022-04-26 05:11:32.001", "at_type": "1", "internal_name": "ZTF22aahqanq", "remarks": "Early SN candidate (r-rise > 0.13+-0.02 mag/day) classified using ALeRCE's stamp classifier (Carrasco-Davis et al. 2021) and the public ZTF stream. Discovery image and light curve in http://alerce.online/object/ZTF22aahqanq ", "non_detection": {"obsdate": "2022-04-24 05:05:00.997", "limiting_flux": "19.7451", "flux_units": "1", "filter_value": "110", "instrument_value": "196", "exptime": "30", "observer": "Robot", "comments": "Data provided by ZTF"}, "photometry": {"photometry_group": {"0": {"obsdate": "2022-04-26 05:11:32.001", "flux": "18.849653", "flux_error": "0.14190333", "limiting_flux": "19.914503", "flux_units": "1", "filter_value": "111", "instrument_value": "196", "exptime": "30", "observer": "Robot", "comments": "Data provided by ZTF"}}}, "host_name": "WISEA J103706.97-163358.8"}, "9": {"ra": {"value": "164.39654073333335", "error": "0.085", "units": "arcsec"}, "dec": {"value": "5.246282466666667", "error": "0.085", "units": "arcsec"}, "reporting_group_id": "74", "discovery_data_source_id": "48", "reporter": "A. Munoz-Arancibia, F. Forster, F.E. Bauer, G. Pignata, A. Mourao, L. Hernandez-Garcia, L. Galbany, R. Hoshino, E. Camacho, J. Silva-Farfan, J. Arredondo, G. Cabrera-Vives, R. Carrasco-Davis, P.A. Estevez, P. Huijse, A. Moya E. Reyes, I. Reyes, P. Sanchez-Saez, D. Rodriguez-Mancini, M. Catelan, S. Eyheramendy, M.J. Graham on behalf of the ALeRCE broker", "discovery_datetime": "2022-04-20 06:08:51.999", "at_type": "1", "internal_name": "ZTF22aahpvzi", "remarks": "SN candidate classified using ALeRCE's stamp classifier (Carrasco-Davis et al. 2021) and the public ZTF stream. Discovery image and light curve in http://alerce.online/object/ZTF22aahpvzi ", "non_detection": {"obsdate": "2022-04-18 06:14:20.000", "limiting_flux": "19.5984", "flux_units": "1", "filter_value": "110", "instrument_value": "196", "exptime": "30", "observer": "Robot", "comments": "Data provided by ZTF"}, "photometry": {"photometry_group": {"0": {"obsdate": "2022-04-20 06:08:51.999", "flux": "20.1793", "flux_error": "0.2947", "limiting_flux": "19.8931", "flux_units": "1", "filter_value": "111", "instrument_value": "196", "exptime": "30", "observer": "Robot", "comments": "Data provided by ZTF"}, "1": {"obsdate": "2022-04-24 05:56:53.998", "flux": "20.0702", "flux_error": "0.226043", "limiting_flux": "20.1584", "flux_units": "1", "filter_value": "110", "instrument_value": "196", "exptime": "30", "observer": "Robot", "comments": "Data provided by ZTF"}, "2": {"obsdate": "2022-04-26 05:03:58.997", "flux": "19.83307", "flux_error": "0.1549197", "limiting_flux": "20.378803", "flux_units": "1", "filter_value": "111", "instrument_value": "196", "exptime": "30", "observer": "Robot", "comments": "Data provided by ZTF"}}}, "host_name": "SDSS J105735.06+051446.5"}, "10": {"ra": {"value": "176.2182098", "error": "0.085", "units": "arcsec"}, "dec": {"value": "25.34538285", "error": "0.085", "units": "arcsec"}, "reporting_group_id": "74", "discovery_data_source_id": "48", "reporter": "A. Munoz-Arancibia, F. Forster, F.E. Bauer, G. Pignata, A. Mourao, L. Hernandez-Garcia, L. Galbany, R. Hoshino, E. Camacho, J. Silva-Farfan, J. Arredondo, G. Cabrera-Vives, R. Carrasco-Davis, P.A. Estevez, P. Huijse, A. Moya E. Reyes, I. Reyes, P. Sanchez-Saez, D. Rodriguez-Mancini, M. Catelan, S. Eyheramendy, M.J. Graham on behalf of the ALeRCE broker", "discovery_datetime": "2022-04-24 05:55:28.998", "at_type": "1", "internal_name": "ZTF22aahpvuk", "remarks": "SN candidate classified using ALeRCE's stamp classifier (Carrasco-Davis et al. 2021) and the public ZTF stream. Discovery image and light curve in http://alerce.online/object/ZTF22aahpvuk ", "non_detection": {"obsdate": "2022-04-20 06:38:02.999", "limiting_flux": "19.8669", "flux_units": "1", "filter_value": "110", "instrument_value": "196", "exptime": "30", "observer": "Robot", "comments": "Data provided by ZTF"}, "photometry": {"photometry_group": {"0": {"obsdate": "2022-04-24 05:55:28.998", "flux": "20.3668", "flux_error": "0.241411", "limiting_flux": "20.4614", "flux_units": "1", "filter_value": "110", "instrument_value": "196", "exptime": "30", "observer": "Robot", "comments": "Data provided by ZTF"}, "1": {"obsdate": "2022-04-26 05:06:43.001", "flux": "20.391935", "flux_error": "0.20452814", "limiting_flux": "20.58965", "flux_units": "1", "filter_value": "111", "instrument_value": "196", "exptime": "30", "observer": "Robot", "comments": "Data provided by ZTF"}}}, "host_name": "WISEA J114451.96+252044.1"}, "11": {"ra": {"value": "131.6272811", "error": "0.085", "units": "arcsec"}, "dec": {"value": "23.920916050000002", "error": "0.085", "units": "arcsec"}, "reporting_group_id": "74", "discovery_data_source_id": "48", "reporter": "A. Munoz-Arancibia, F. Forster, F.E. Bauer, G. Pignata, A. Mourao, L. Hernandez-Garcia, L. Galbany, R. Hoshino, E. Camacho, J. Silva-Farfan, J. Arredondo, G. Cabrera-Vives, R. Carrasco-Davis, P.A. Estevez, P. Huijse, A. Moya E. Reyes, I. Reyes, P. Sanchez-Saez, D. Rodriguez-Mancini, M. Catelan, S. Eyheramendy, M.J. Graham on behalf of the ALeRCE broker", "discovery_datetime": "2022-04-26 04:29:45.001", "at_type": "1", "internal_name": "ZTF22aahpcur", "remarks": "SN candidate classified using ALeRCE's stamp classifier (Carrasco-Davis et al. 2021) and the public ZTF stream. Discovery image and light curve in http://alerce.online/object/ZTF22aahpcur ", "non_detection": {"obsdate": "2022-04-24 04:27:27.996", "limiting_flux": "19.8925", "flux_units": "1", "filter_value": "111", "instrument_value": "196", "exptime": "30", "observer": "Robot", "comments": "Data provided by ZTF"}, "photometry": {"photometry_group": {"0": {"obsdate": "2022-04-26 04:29:45.001", "flux": "19.818806", "flux_error": "0.14986707", "limiting_flux": "20.294222", "flux_units": "1", "filter_value": "110", "instrument_value": "196", "exptime": "30", "observer": "Robot", "comments": "Data provided by ZTF"}, "1": {"obsdate": "2022-04-26 04:45:04.997", "flux": "19.844961", "flux_error": "0.20835121", "limiting_flux": "20.062914", "flux_units": "1", "filter_value": "111", "instrument_value": "196", "exptime": "30", "observer": "Robot", "comments": "Data provided by ZTF"}}}, "host_name": "SDSS J084630.51+235514.4"}, "12": {"ra": {"value": "157.6453505", "error": "0.085", "units": "arcsec"}, "dec": {"value": "-5.4804545", "error": "0.085", "units": "arcsec"}, "reporting_group_id": "74", "discovery_data_source_id": "48", "reporter": "A. Munoz-Arancibia, F. Forster, F.E. Bauer, G. Pignata, A. Mourao, L. Hernandez-Garcia, L. Galbany, R. Hoshino, E. Camacho, J. Silva-Farfan, J. Arredondo, G. Cabrera-Vives, R. Carrasco-Davis, P.A. Estevez, P. Huijse, A. Moya E. Reyes, I. Reyes, P. Sanchez-Saez, D. Rodriguez-Mancini, M. Catelan, S. Eyheramendy, M.J. Graham on behalf of the ALeRCE broker", "discovery_datetime": "2022-04-26 06:09:13.003", "at_type": "1", "internal_name": "ZTF19acfrusu", "remarks": "Early SN candidate (g-rise > 0.98+-0.08 mag/day) classified using ALeRCE's stamp classifier (Carrasco-Davis et al. 2021) and the public ZTF stream. Discovery image and light curve in http://alerce.online/object/ZTF19acfrusu ", "non_detection": {"obsdate": "2022-04-26 04:34:11.001", "limiting_flux": "19.8388", "flux_units": "1", "filter_value": "111", "instrument_value": "196", "exptime": "30", "observer": "Robot", "comments": "Data provided by ZTF"}, "photometry": {"photometry_group": {"0": {"obsdate": "2022-04-26 06:09:13.003", "flux": "18.050316", "flux_error": "0.16307387", "limiting_flux": "18.1939", "flux_units": "1", "filter_value": "110", "instrument_value": "196", "exptime": "30", "observer": "Robot", "comments": "Data provided by ZTF"}}}, "host_name": "WISEA J103034.88-052849.0", "host_redshift": "0.04691"}}}