{"at_report": {"0": {"ra": {"value": "229.198691", "error": "0.085", "units": "arcsec"}, "dec": {"value": "-15.8901293", "error": "0.085", "units": "arcsec"}, "reporting_group_id": "74", "discovery_data_source_id": "48", "reporter": "A. Munoz-Arancibia, F.E. Bauer, G. Pignata, F. Forster, A. Mourao, L. Hernandez-Garcia, L. Galbany, J. Silva-Farfan, R. Dastidar, J.P. Brandt, A. Alvarez, G. Cabrera-Vives, R. Carrasco-Davis, P.A. Estevez, B. Gamboa, P. Huijse, H. Larranaga, C. Mansilla, K. Medina, D. Moreno, E. Munoz, I. Reyes, P. Sanchez-Saez, D. Rodriguez-Mancini, M. Catelan, S. Eyheramendy, M.J. Graham on behalf of the ALeRCE broker", "discovery_datetime": "2025-01-17 12:55:46.998", "at_type": "1", "internal_name": "ZTF25aacdnrt", "remarks": "SN candidate classified using ALeRCE's stamp classifier (Carrasco-Davis et al. 2021) and the public ZTF stream. Discovery image and light curve in http://alerce.online/object/ZTF25aacdnrt ", "non_detection": {"obsdate": "2024-12-24 13:34:40.999", "limiting_flux": "16.3115", "flux_units": "1", "filter_value": "111", "instrument_value": "196", "exptime": "30", "observer": "Robot", "comments": "Data provided by ZTF"}, "photometry": {"photometry_group": {"0": {"obsdate": "2025-01-17 12:55:46.998", "flux": "18.670744", "flux_error": "0.14350192", "limiting_flux": "19.077988", "flux_units": "1", "filter_value": "110", "instrument_value": "196", "exptime": "30", "observer": "Robot", "comments": "Data provided by ZTF"}}}, "host_name": "WISEA J151647.64-155325.9"}, "1": {"ra": {"value": "239.743227", "error": "0.14827513694763184", "units": "arcsec"}, "dec": {"value": "55.0222253", "error": "0.14827513694763184", "units": "arcsec"}, "reporting_group_id": "74", "discovery_data_source_id": "48", "reporter": "A. Munoz-Arancibia, F.E. Bauer, G. Pignata, F. Forster, A. Mourao, L. Hernandez-Garcia, L. Galbany, J. Silva-Farfan, R. Dastidar, J.P. Brandt, A. Alvarez, G. Cabrera-Vives, R. Carrasco-Davis, P.A. Estevez, B. Gamboa, P. Huijse, H. Larranaga, C. Mansilla, K. Medina, D. Moreno, E. Munoz, I. Reyes, P. Sanchez-Saez, D. Rodriguez-Mancini, M. Catelan, S. Eyheramendy, M.J. Graham on behalf of the ALeRCE broker", "discovery_datetime": "2025-01-17 12:21:11.998", "at_type": "1", "internal_name": "ZTF25aacdlqg", "remarks": "SN candidate classified using ALeRCE's stamp classifier (Carrasco-Davis et al. 2021) and the public ZTF stream. Discovery image and light curve in http://alerce.online/object/ZTF25aacdlqg ", "non_detection": {"obsdate": "2025-01-17 10:48:28.002", "limiting_flux": "19.4858", "flux_units": "1", "filter_value": "110", "instrument_value": "196", "exptime": "30", "observer": "Robot", "comments": "Data provided by ZTF"}, "photometry": {"photometry_group": {"0": {"obsdate": "2025-01-17 12:21:11.998", "flux": "20.054398", "flux_error": "0.20745158", "limiting_flux": "19.931576", "flux_units": "1", "filter_value": "111", "instrument_value": "196", "exptime": "30", "observer": "Robot", "comments": "Data provided by ZTF"}}}, "host_name": "SDSS J155858.33+550119.8"}, "2": {"ra": {"value": "254.48940101962467", "error": "0.085", "units": "arcsec"}, "dec": {"value": "38.50783954760429", "error": "0.085", "units": "arcsec"}, "reporting_group_id": "74", "discovery_data_source_id": "48", "reporter": "A. Munoz-Arancibia, F.E. Bauer, G. Pignata, F. Forster, A. Mourao, L. Hernandez-Garcia, L. Galbany, J. Silva-Farfan, R. Dastidar, J.P. Brandt, A. Alvarez, G. Cabrera-Vives, R. Carrasco-Davis, P.A. Estevez, B. Gamboa, P. Huijse, H. Larranaga, C. Mansilla, K. Medina, D. Moreno, E. Munoz, I. Reyes, P. Sanchez-Saez, D. Rodriguez-Mancini, M. Catelan, S. Eyheramendy, M.J. Graham on behalf of the ALeRCE broker", "discovery_datetime": "2025-01-15 12:44:38.996", "at_type": "1", "internal_name": "ZTF25aacdlqc", "remarks": "Early SN candidate (r-rise > 0.07+-0.02 mag/day) classified using ALeRCE's stamp classifier (Carrasco-Davis et al. 2021) and the public ZTF stream. Discovery image and light curve in http://alerce.online/object/ZTF25aacdlqc ", "non_detection": {"obsdate": "2025-01-12 13:11:30.002", "limiting_flux": "18.9969", "flux_units": "1", "filter_value": "110", "instrument_value": "196", "exptime": "30", "observer": "Robot", "comments": "Data provided by ZTF"}, "photometry": {"photometry_group": {"0": {"obsdate": "2025-01-15 12:44:38.996", "flux": "19.0112", "flux_error": "0.268944", "limiting_flux": "18.7164", "flux_units": "1", "filter_value": "110", "instrument_value": "196", "exptime": "30", "observer": "Robot", "comments": "Data provided by ZTF"}, "1": {"obsdate": "2025-01-17 12:21:56.002", "flux": "19.395142", "flux_error": "0.17396376", "limiting_flux": "19.531698", "flux_units": "1", "filter_value": "111", "instrument_value": "196", "exptime": "30", "observer": "Robot", "comments": "Data provided by ZTF"}}}, "host_name": "SDSS J165757.52+383027.9"}, "3": {"ra": {"value": "232.45658", "error": "0.1381189078092575", "units": "arcsec"}, "dec": {"value": "52.0181522", "error": "0.1381189078092575", "units": "arcsec"}, "reporting_group_id": "74", "discovery_data_source_id": "48", "reporter": "A. Munoz-Arancibia, F.E. Bauer, G. Pignata, F. Forster, A. Mourao, L. Hernandez-Garcia, L. Galbany, J. Silva-Farfan, R. Dastidar, J.P. Brandt, A. Alvarez, G. Cabrera-Vives, R. Carrasco-Davis, P.A. Estevez, B. Gamboa, P. Huijse, H. Larranaga, C. Mansilla, K. Medina, D. Moreno, E. Munoz, I. Reyes, P. Sanchez-Saez, D. Rodriguez-Mancini, M. Catelan, S. Eyheramendy, M.J. Graham on behalf of the ALeRCE broker", "discovery_datetime": "2025-01-17 12:21:11.998", "at_type": "1", "internal_name": "ZTF25aacdlpf", "remarks": "SN candidate classified using ALeRCE's stamp classifier (Carrasco-Davis et al. 2021) and the public ZTF stream. Discovery image and light curve in http://alerce.online/object/ZTF25aacdlpf ", "non_detection": {"obsdate": "2025-01-17 10:48:28.002", "limiting_flux": "19.4743", "flux_units": "1", "filter_value": "110", "instrument_value": "196", "exptime": "30", "observer": "Robot", "comments": "Data provided by ZTF"}, "photometry": {"photometry_group": {"0": {"obsdate": "2025-01-17 12:21:11.998", "flux": "19.792372", "flux_error": "0.19136776", "limiting_flux": "19.913088", "flux_units": "1", "filter_value": "111", "instrument_value": "196", "exptime": "30", "observer": "Robot", "comments": "Data provided by ZTF"}}}, "host_name": "SDSS J152949.77+520107.3"}, "4": {"ra": {"value": "249.0795596", "error": "0.2319727540016174", "units": "arcsec"}, "dec": {"value": "68.5048571", "error": "0.2319727540016174", "units": "arcsec"}, "reporting_group_id": "74", "discovery_data_source_id": "48", "reporter": "A. Munoz-Arancibia, F.E. Bauer, G. Pignata, F. Forster, A. Mourao, L. Hernandez-Garcia, L. Galbany, J. Silva-Farfan, R. Dastidar, J.P. Brandt, A. Alvarez, G. Cabrera-Vives, R. Carrasco-Davis, P.A. Estevez, B. Gamboa, P. Huijse, H. Larranaga, C. Mansilla, K. Medina, D. Moreno, E. Munoz, I. Reyes, P. Sanchez-Saez, D. Rodriguez-Mancini, M. Catelan, S. Eyheramendy, M.J. Graham on behalf of the ALeRCE broker", "discovery_datetime": "2025-01-17 11:54:26.004", "at_type": "1", "internal_name": "ZTF25aacdkws", "remarks": "SN candidate classified using ALeRCE's stamp classifier (Carrasco-Davis et al. 2021) and the public ZTF stream. Discovery image and light curve in http://alerce.online/object/ZTF25aacdkws ", "non_detection": {"obsdate": "2025-01-15 11:48:16.998", "limiting_flux": "19.0252", "flux_units": "1", "filter_value": "111", "instrument_value": "196", "exptime": "30", "observer": "Robot", "comments": "Data provided by ZTF"}, "photometry": {"photometry_group": {"0": {"obsdate": "2025-01-17 11:54:26.004", "flux": "19.881409", "flux_error": "0.18569137", "limiting_flux": "19.737864", "flux_units": "1", "filter_value": "111", "instrument_value": "196", "exptime": "30", "observer": "Robot", "comments": "Data provided by ZTF"}}}, "host_name": "WISEA J163619.20+683017.7"}, "5": {"ra": {"value": "217.09711941212768", "error": "0.085", "units": "arcsec"}, "dec": {"value": "33.03835278848612", "error": "0.085", "units": "arcsec"}, "reporting_group_id": "74", "discovery_data_source_id": "48", "reporter": "A. Munoz-Arancibia, F.E. Bauer, G. Pignata, F. Forster, A. Mourao, L. Hernandez-Garcia, L. Galbany, J. Silva-Farfan, R. Dastidar, J.P. Brandt, A. Alvarez, G. Cabrera-Vives, R. Carrasco-Davis, P.A. Estevez, B. Gamboa, P. Huijse, H. Larranaga, C. Mansilla, K. Medina, D. Moreno, E. Munoz, I. Reyes, P. Sanchez-Saez, D. Rodriguez-Mancini, M. Catelan, S. Eyheramendy, M.J. Graham on behalf of the ALeRCE broker", "discovery_datetime": "2025-01-15 12:22:39.996", "at_type": "1", "internal_name": "ZTF25aacdkan", "remarks": "SN candidate classified using ALeRCE's stamp classifier (Carrasco-Davis et al. 2021) and the public ZTF stream. Discovery image and light curve in http://alerce.online/object/ZTF25aacdkan ", "non_detection": {"obsdate": "2025-01-12 12:14:22.998", "limiting_flux": "19.5631", "flux_units": "1", "filter_value": "111", "instrument_value": "196", "exptime": "30", "observer": "Robot", "comments": "Data provided by ZTF"}, "photometry": {"photometry_group": {"0": {"obsdate": "2025-01-15 12:22:39.996", "flux": "19.6551", "flux_error": "0.255653", "limiting_flux": "19.4701", "flux_units": "1", "filter_value": "111", "instrument_value": "196", "exptime": "30", "observer": "Robot", "comments": "Data provided by ZTF"}, "1": {"obsdate": "2025-01-15 12:57:52.001", "flux": "19.706", "flux_error": "0.333574", "limiting_flux": "19.2114", "flux_units": "1", "filter_value": "110", "instrument_value": "196", "exptime": "30", "observer": "Robot", "comments": "Data provided by ZTF"}, "2": {"obsdate": "2025-01-17 11:29:18.004", "flux": "19.508427", "flux_error": "0.16344272", "limiting_flux": "19.652187", "flux_units": "1", "filter_value": "110", "instrument_value": "196", "exptime": "30", "observer": "Robot", "comments": "Data provided by ZTF"}}}, "host_name": "SDSS J142823.49+330219.4"}, "6": {"ra": {"value": "234.32236450000826", "error": "0.085", "units": "arcsec"}, "dec": {"value": "27.07463635", "error": "0.085", "units": "arcsec"}, "reporting_group_id": "74", "discovery_data_source_id": "48", "reporter": "A. Munoz-Arancibia, F.E. Bauer, G. Pignata, F. Forster, A. Mourao, L. Hernandez-Garcia, L. Galbany, J. Silva-Farfan, R. Dastidar, J.P. Brandt, A. Alvarez, G. Cabrera-Vives, R. Carrasco-Davis, P.A. Estevez, B. Gamboa, P. Huijse, H. Larranaga, C. Mansilla, K. Medina, D. Moreno, E. Munoz, I. Reyes, P. Sanchez-Saez, D. Rodriguez-Mancini, M. Catelan, S. Eyheramendy, M.J. Graham on behalf of the ALeRCE broker", "discovery_datetime": "2025-01-15 10:41:31.001", "at_type": "1", "internal_name": "ZTF25aacdjzy", "remarks": "Early SN candidate (g-rise > 0.17+-0.03 mag/day) classified using ALeRCE's stamp classifier (Carrasco-Davis et al. 2021) and the public ZTF stream. Discovery image and light curve in http://alerce.online/object/ZTF25aacdjzy ", "non_detection": {"obsdate": "2025-01-12 12:26:10.000", "limiting_flux": "19.4374", "flux_units": "1", "filter_value": "111", "instrument_value": "196", "exptime": "30", "observer": "Robot", "comments": "Data provided by ZTF"}, "photometry": {"photometry_group": {"0": {"obsdate": "2025-01-15 10:41:31.001", "flux": "18.6631", "flux_error": "0.289712", "limiting_flux": "18.2092", "flux_units": "1", "filter_value": "110", "instrument_value": "196", "exptime": "30", "observer": "Robot", "comments": "Data provided by ZTF"}, "1": {"obsdate": "2025-01-17 11:27:15.998", "flux": "19.029978", "flux_error": "0.14004117", "limiting_flux": "19.48426", "flux_units": "1", "filter_value": "110", "instrument_value": "196", "exptime": "30", "observer": "Robot", "comments": "Data provided by ZTF"}}}, "host_name": "SDSS J153717.47+270426.5", "host_redshift": "0.09472493"}, "7": {"ra": {"value": "245.80948826821125", "error": "0.085", "units": "arcsec"}, "dec": {"value": "40.922184776839856", "error": "0.085", "units": "arcsec"}, "reporting_group_id": "74", "discovery_data_source_id": "48", "reporter": "A. Munoz-Arancibia, F.E. Bauer, G. Pignata, F. Forster, A. Mourao, L. Hernandez-Garcia, L. Galbany, J. Silva-Farfan, R. Dastidar, J.P. Brandt, A. Alvarez, G. Cabrera-Vives, R. Carrasco-Davis, P.A. Estevez, B. Gamboa, P. Huijse, H. Larranaga, C. Mansilla, K. Medina, D. Moreno, E. Munoz, I. Reyes, P. Sanchez-Saez, D. Rodriguez-Mancini, M. Catelan, S. Eyheramendy, M.J. Graham on behalf of the ALeRCE broker", "discovery_datetime": "2025-01-15 11:18:27.999", "at_type": "1", "internal_name": "ZTF25aacdjzo", "remarks": "Early SN candidate (r-rise > 0.12+-0.02 mag/day) classified using ALeRCE's stamp classifier (Carrasco-Davis et al. 2021) and the public ZTF stream. Discovery image and light curve in http://alerce.online/object/ZTF25aacdjzo ", "non_detection": {"obsdate": "2025-01-12 12:50:59.001", "limiting_flux": "18.7939", "flux_units": "1", "filter_value": "110", "instrument_value": "196", "exptime": "30", "observer": "Robot", "comments": "Data provided by ZTF"}, "photometry": {"photometry_group": {"0": {"obsdate": "2025-01-15 11:18:27.999", "flux": "18.9727", "flux_error": "0.33241", "limiting_flux": "18.5202", "flux_units": "1", "filter_value": "110", "instrument_value": "196", "exptime": "30", "observer": "Robot", "comments": "Data provided by ZTF"}, "1": {"obsdate": "2025-01-17 11:25:50.998", "flux": "18.824879", "flux_error": "0.11636509", "limiting_flux": "19.458652", "flux_units": "1", "filter_value": "110", "instrument_value": "196", "exptime": "30", "observer": "Robot", "comments": "Data provided by ZTF"}, "2": {"obsdate": "2025-01-17 11:55:57.000", "flux": "18.671022", "flux_error": "0.09190096", "limiting_flux": "19.800776", "flux_units": "1", "filter_value": "111", "instrument_value": "196", "exptime": "30", "observer": "Robot", "comments": "Data provided by ZTF"}}}, "host_name": "SDSS J162314.32+405519.1"}, "8": {"ra": {"value": "188.7882785500449", "error": "0.085", "units": "arcsec"}, "dec": {"value": "52.770448", "error": "0.085", "units": "arcsec"}, "reporting_group_id": "74", "discovery_data_source_id": "48", "reporter": "A. Munoz-Arancibia, F.E. Bauer, G. Pignata, F. Forster, A. Mourao, L. Hernandez-Garcia, L. Galbany, J. Silva-Farfan, R. Dastidar, J.P. Brandt, A. Alvarez, G. Cabrera-Vives, R. Carrasco-Davis, P.A. Estevez, B. Gamboa, P. Huijse, H. Larranaga, C. Mansilla, K. Medina, D. Moreno, E. Munoz, I. Reyes, P. Sanchez-Saez, D. Rodriguez-Mancini, M. Catelan, S. Eyheramendy, M.J. Graham on behalf of the ALeRCE broker", "discovery_datetime": "2025-01-15 11:28:17.999", "at_type": "1", "internal_name": "ZTF25aacdipy", "remarks": "Early SN candidate (g-rise > 0.08+-0.02 mag/day) classified using ALeRCE's stamp classifier (Carrasco-Davis et al. 2021) and the public ZTF stream. Discovery image and light curve in http://alerce.online/object/ZTF25aacdipy ", "non_detection": {"obsdate": "2025-01-13 12:18:52.004", "limiting_flux": "18.0996", "flux_units": "1", "filter_value": "111", "instrument_value": "196", "exptime": "30", "observer": "Robot", "comments": "Data provided by ZTF"}, "photometry": {"photometry_group": {"0": {"obsdate": "2025-01-15 11:28:17.999", "flux": "19.3581", "flux_error": "0.272286", "limiting_flux": "19.008", "flux_units": "1", "filter_value": "110", "instrument_value": "196", "exptime": "30", "observer": "Robot", "comments": "Data provided by ZTF"}, "1": {"obsdate": "2025-01-17 10:44:56.996", "flux": "19.852316", "flux_error": "0.21061607", "limiting_flux": "19.485119", "flux_units": "1", "filter_value": "110", "instrument_value": "196", "exptime": "30", "observer": "Robot", "comments": "Data provided by ZTF"}}}, "host_name": "SDSS J123509.16+524613.5"}, "9": {"ra": {"value": "166.56161699999998", "error": "0.2354750782251358", "units": "arcsec"}, "dec": {"value": "68.840074", "error": "0.2354750782251358", "units": "arcsec"}, "reporting_group_id": "74", "discovery_data_source_id": "48", "reporter": "A. Munoz-Arancibia, F.E. Bauer, G. Pignata, F. Forster, A. Mourao, L. Hernandez-Garcia, L. Galbany, J. Silva-Farfan, R. Dastidar, J.P. Brandt, A. Alvarez, G. Cabrera-Vives, R. Carrasco-Davis, P.A. Estevez, B. Gamboa, P. Huijse, H. Larranaga, C. Mansilla, K. Medina, D. Moreno, E. Munoz, I. Reyes, P. Sanchez-Saez, D. Rodriguez-Mancini, M. Catelan, S. Eyheramendy, M.J. Graham on behalf of the ALeRCE broker", "discovery_datetime": "2025-01-17 10:10:24.001", "at_type": "1", "internal_name": "ZTF25aacdheo", "remarks": "SN candidate classified using ALeRCE's stamp classifier (Carrasco-Davis et al. 2021) and the public ZTF stream. Discovery image and light curve in http://alerce.online/object/ZTF25aacdheo ", "non_detection": {"obsdate": "2025-01-15 09:46:46.004", "limiting_flux": "19.3212", "flux_units": "1", "filter_value": "111", "instrument_value": "196", "exptime": "30", "observer": "Robot", "comments": "Data provided by ZTF"}, "photometry": {"photometry_group": {"0": {"obsdate": "2025-01-17 10:10:24.001", "flux": "20.072058", "flux_error": "0.19716993", "limiting_flux": "19.885036", "flux_units": "1", "filter_value": "111", "instrument_value": "196", "exptime": "30", "observer": "Robot", "comments": "Data provided by ZTF"}}}}, "10": {"ra": {"value": "79.7371249", "error": "0.08568669110536575", "units": "arcsec"}, "dec": {"value": "-7.2585701", "error": "0.08568669110536575", "units": "arcsec"}, "reporting_group_id": "74", "discovery_data_source_id": "48", "reporter": "A. Munoz-Arancibia, F.E. Bauer, G. Pignata, F. Forster, A. Mourao, L. Hernandez-Garcia, L. Galbany, J. Silva-Farfan, R. Dastidar, J.P. Brandt, A. Alvarez, G. Cabrera-Vives, R. Carrasco-Davis, P.A. Estevez, B. Gamboa, P. Huijse, H. Larranaga, C. Mansilla, K. Medina, D. Moreno, E. Munoz, I. Reyes, P. Sanchez-Saez, D. Rodriguez-Mancini, M. Catelan, S. Eyheramendy, M.J. Graham on behalf of the ALeRCE broker", "discovery_datetime": "2025-01-17 07:49:39.999", "at_type": "1", "internal_name": "ZTF25aaccqfa", "remarks": "Early SN candidate (r-rise > 0.07+-0.01 mag/day) classified using ALeRCE's stamp classifier (Carrasco-Davis et al. 2021) and the public ZTF stream. Discovery image and light curve in http://alerce.online/object/ZTF25aaccqfa ", "non_detection": {"obsdate": "2025-01-15 06:34:55.001", "limiting_flux": "18.6802", "flux_units": "1", "filter_value": "111", "instrument_value": "196", "exptime": "30", "observer": "Robot", "comments": "Data provided by ZTF"}, "photometry": {"photometry_group": {"0": {"obsdate": "2025-01-17 07:49:39.999", "flux": "19.299133", "flux_error": "0.15810074", "limiting_flux": "19.637974", "flux_units": "1", "filter_value": "111", "instrument_value": "196", "exptime": "30", "observer": "Robot", "comments": "Data provided by ZTF"}}}, "host_name": "WISEA J051856.76-071530.8"}, "11": {"ra": {"value": "117.39296409649762", "error": "0.150740023826755", "units": "arcsec"}, "dec": {"value": "69.96879622510923", "error": "0.150740023826755", "units": "arcsec"}, "reporting_group_id": "74", "discovery_data_source_id": "48", "reporter": "A. Munoz-Arancibia, F.E. Bauer, G. Pignata, F. Forster, A. Mourao, L. Hernandez-Garcia, L. Galbany, J. Silva-Farfan, R. Dastidar, J.P. Brandt, A. Alvarez, G. Cabrera-Vives, R. Carrasco-Davis, P.A. Estevez, B. Gamboa, P. Huijse, H. Larranaga, C. Mansilla, K. Medina, D. Moreno, E. Munoz, I. Reyes, P. Sanchez-Saez, D. Rodriguez-Mancini, M. Catelan, S. Eyheramendy, M.J. Graham on behalf of the ALeRCE broker", "discovery_datetime": "2025-01-17 06:28:22.002", "at_type": "1", "internal_name": "ZTF25aacbvcx", "remarks": "Early SN candidate (r-rise > 0.11+-0.02 mag/day) classified using ALeRCE's stamp classifier (Carrasco-Davis et al. 2021) and the public ZTF stream. Discovery image and light curve in http://alerce.online/object/ZTF25aacbvcx ", "non_detection": {"obsdate": "2025-01-15 08:39:39.997", "limiting_flux": "18.7328", "flux_units": "1", "filter_value": "110", "instrument_value": "196", "exptime": "30", "observer": "Robot", "comments": "Data provided by ZTF"}, "photometry": {"photometry_group": {"0": {"obsdate": "2025-01-17 06:28:22.002", "flux": "19.427181", "flux_error": "0.18846287", "limiting_flux": "19.680864", "flux_units": "1", "filter_value": "110", "instrument_value": "196", "exptime": "30", "observer": "Robot", "comments": "Data provided by ZTF"}, "1": {"obsdate": "2025-01-17 06:38:35.002", "flux": "19.198843", "flux_error": "0.103183255", "limiting_flux": "20.00324", "flux_units": "1", "filter_value": "111", "instrument_value": "196", "exptime": "30", "observer": "Robot", "comments": "Data provided by ZTF"}}}, "host_name": "WISEA J074933.99+695809.2"}, "12": {"ra": {"value": "134.0441396000727", "error": "0.085", "units": "arcsec"}, "dec": {"value": "51.026116862080414", "error": "0.085", "units": "arcsec"}, "reporting_group_id": "74", "discovery_data_source_id": "48", "reporter": "A. Munoz-Arancibia, F.E. Bauer, G. Pignata, F. Forster, A. Mourao, L. Hernandez-Garcia, L. Galbany, J. Silva-Farfan, R. Dastidar, J.P. Brandt, A. Alvarez, G. Cabrera-Vives, R. Carrasco-Davis, P.A. Estevez, B. Gamboa, P. Huijse, H. Larranaga, C. Mansilla, K. Medina, D. Moreno, E. Munoz, I. Reyes, P. Sanchez-Saez, D. Rodriguez-Mancini, M. Catelan, S. Eyheramendy, M.J. Graham on behalf of the ALeRCE broker", "discovery_datetime": "2025-01-11 06:48:11.998", "at_type": "1", "internal_name": "ZTF25aacblvq", "remarks": "SN candidate classified using ALeRCE's stamp classifier (Carrasco-Davis et al. 2021) and the public ZTF stream. Discovery image and light curve in http://alerce.online/object/ZTF25aacblvq ", "non_detection": {"obsdate": "2025-01-11 06:06:50.003", "limiting_flux": "19.2826", "flux_units": "1", "filter_value": "110", "instrument_value": "196", "exptime": "30", "observer": "Robot", "comments": "Data provided by ZTF"}, "photometry": {"photometry_group": {"0": {"obsdate": "2025-01-11 06:48:11.998", "flux": "20.0476", "flux_error": "0.348014", "limiting_flux": "19.6033", "flux_units": "1", "filter_value": "110", "instrument_value": "196", "exptime": "30", "observer": "Robot", "comments": "Data provided by ZTF"}, "1": {"obsdate": "2025-01-11 08:48:54.996", "flux": "20.0253", "flux_error": "0.281685", "limiting_flux": "19.7231", "flux_units": "1", "filter_value": "111", "instrument_value": "196", "exptime": "30", "observer": "Robot", "comments": "Data provided by ZTF"}, "2": {"obsdate": "2025-01-17 06:14:15.999", "flux": "19.5089", "flux_error": "0.241197", "limiting_flux": "19.5235", "flux_units": "1", "filter_value": "110", "instrument_value": "196", "exptime": "30", "observer": "Robot", "comments": "Data provided by ZTF"}, "3": {"obsdate": "2025-01-17 06:42:43.998", "flux": "19.8019", "flux_error": "0.237526", "limiting_flux": "19.7249", "flux_units": "1", "filter_value": "111", "instrument_value": "196", "exptime": "30", "observer": "Robot", "comments": "Data provided by ZTF"}, "4": {"obsdate": "2025-01-17 07:12:02.998", "flux": "19.8724", "flux_error": "0.221054", "limiting_flux": "19.7262", "flux_units": "1", "filter_value": "111", "instrument_value": "196", "exptime": "30", "observer": "Robot", "comments": "Data provided by ZTF"}, "5": {"obsdate": "2025-01-17 08:14:31.998", "flux": "19.510918", "flux_error": "0.21618252", "limiting_flux": "19.765385", "flux_units": "1", "filter_value": "110", "instrument_value": "196", "exptime": "30", "observer": "Robot", "comments": "Data provided by ZTF"}}}, "host_name": "SDSS J085610.49+510134.4"}, "13": {"ra": {"value": "53.4206465", "error": "0.11570312082767488", "units": "arcsec"}, "dec": {"value": "42.7232987", "error": "0.11570312082767488", "units": "arcsec"}, "reporting_group_id": "74", "discovery_data_source_id": "48", "reporter": "A. Munoz-Arancibia, F.E. Bauer, G. Pignata, F. Forster, A. Mourao, L. Hernandez-Garcia, L. Galbany, J. Silva-Farfan, R. Dastidar, J.P. Brandt, A. Alvarez, G. Cabrera-Vives, R. Carrasco-Davis, P.A. Estevez, B. Gamboa, P. Huijse, H. Larranaga, C. Mansilla, K. Medina, D. Moreno, E. Munoz, I. Reyes, P. Sanchez-Saez, D. Rodriguez-Mancini, M. Catelan, S. Eyheramendy, M.J. Graham on behalf of the ALeRCE broker", "discovery_datetime": "2025-01-17 04:56:49.001", "at_type": "1", "internal_name": "ZTF25aacbhct", "remarks": "Early SN candidate (r-rise > 0.23+-0.02 mag/day) classified using ALeRCE's stamp classifier (Carrasco-Davis et al. 2021) and the public ZTF stream. Discovery image and light curve in http://alerce.online/object/ZTF25aacbhct ", "non_detection": {"obsdate": "2025-01-15 05:24:16.001", "limiting_flux": "18.8968", "flux_units": "1", "filter_value": "110", "instrument_value": "196", "exptime": "30", "observer": "Robot", "comments": "Data provided by ZTF"}, "photometry": {"photometry_group": {"0": {"obsdate": "2025-01-17 04:56:49.001", "flux": "18.599522", "flux_error": "0.09418174", "limiting_flux": "19.703482", "flux_units": "1", "filter_value": "111", "instrument_value": "196", "exptime": "30", "observer": "Robot", "comments": "Data provided by ZTF"}}}}, "14": {"ra": {"value": "114.1975057221007", "error": "0.085", "units": "arcsec"}, "dec": {"value": "63.01353634781869", "error": "0.085", "units": "arcsec"}, "reporting_group_id": "74", "discovery_data_source_id": "48", "reporter": "A. Munoz-Arancibia, F.E. Bauer, G. Pignata, F. Forster, A. Mourao, L. Hernandez-Garcia, L. Galbany, J. Silva-Farfan, R. Dastidar, J.P. Brandt, A. Alvarez, G. Cabrera-Vives, R. Carrasco-Davis, P.A. Estevez, B. Gamboa, P. Huijse, H. Larranaga, C. Mansilla, K. Medina, D. Moreno, E. Munoz, I. Reyes, P. Sanchez-Saez, D. Rodriguez-Mancini, M. Catelan, S. Eyheramendy, M.J. Graham on behalf of the ALeRCE broker", "discovery_datetime": "2025-01-11 05:49:33.004", "at_type": "1", "internal_name": "ZTF25aabzbex", "remarks": "Early SN candidate (r-rise > 0.07+-0.02 mag/day) classified using ALeRCE's stamp classifier (Carrasco-Davis et al. 2021) and the public ZTF stream. Discovery image and light curve in http://alerce.online/object/ZTF25aabzbex ", "non_detection": {"obsdate": "2025-01-08 10:28:44.996", "limiting_flux": "19.3179", "flux_units": "1", "filter_value": "110", "instrument_value": "196", "exptime": "30", "observer": "Robot", "comments": "Data provided by ZTF"}, "photometry": {"photometry_group": {"0": {"obsdate": "2025-01-11 05:49:33.004", "flux": "19.8738", "flux_error": "0.310962", "limiting_flux": "19.3545", "flux_units": "1", "filter_value": "110", "instrument_value": "196", "exptime": "30", "observer": "Robot", "comments": "Data provided by ZTF"}, "1": {"obsdate": "2025-01-13 05:41:19.003", "flux": "19.4629", "flux_error": "0.261869", "limiting_flux": "19.0", "flux_units": "1", "filter_value": "111", "instrument_value": "196", "exptime": "30", "observer": "Robot", "comments": "Data provided by ZTF"}, "2": {"obsdate": "2025-01-15 07:48:09.996", "flux": "19.7335", "flux_error": "0.279236", "limiting_flux": "19.3109", "flux_units": "1", "filter_value": "111", "instrument_value": "196", "exptime": "30", "observer": "Robot", "comments": "Data provided by ZTF"}, "3": {"obsdate": "2025-01-17 06:27:41.999", "flux": "19.778368", "flux_error": "0.18444033", "limiting_flux": "19.781164", "flux_units": "1", "filter_value": "110", "instrument_value": "196", "exptime": "30", "observer": "Robot", "comments": "Data provided by ZTF"}}}}, "15": {"ra": {"value": "121.9631932001087", "error": "0.09095265674206446", "units": "arcsec"}, "dec": {"value": "48.6369363", "error": "0.09095265674206446", "units": "arcsec"}, "reporting_group_id": "74", "discovery_data_source_id": "48", "reporter": "A. Munoz-Arancibia, F.E. Bauer, G. Pignata, F. Forster, A. Mourao, L. Hernandez-Garcia, L. Galbany, J. Silva-Farfan, R. Dastidar, J.P. Brandt, A. Alvarez, G. Cabrera-Vives, R. Carrasco-Davis, P.A. Estevez, B. Gamboa, P. Huijse, H. Larranaga, C. Mansilla, K. Medina, D. Moreno, E. Munoz, I. Reyes, P. Sanchez-Saez, D. Rodriguez-Mancini, M. Catelan, S. Eyheramendy, M.J. Graham on behalf of the ALeRCE broker", "discovery_datetime": "2025-01-11 09:43:29.004", "at_type": "1", "internal_name": "ZTF25aaaoinj", "remarks": "SN candidate classified using ALeRCE's stamp classifier (Carrasco-Davis et al. 2021) and the public ZTF stream. Discovery image and light curve in http://alerce.online/object/ZTF25aaaoinj ", "non_detection": {"obsdate": "2025-01-11 06:41:37.003", "limiting_flux": "18.7062", "flux_units": "1", "filter_value": "110", "instrument_value": "196", "exptime": "30", "observer": "Robot", "comments": "Data provided by ZTF"}, "photometry": {"photometry_group": {"0": {"obsdate": "2025-01-11 09:43:29.004", "flux": "19.9255", "flux_error": "0.247662", "limiting_flux": "19.5435", "flux_units": "1", "filter_value": "111", "instrument_value": "196", "exptime": "30", "observer": "Robot", "comments": "Data provided by ZTF"}, "1": {"obsdate": "2025-01-17 07:23:16.996", "flux": "19.96673", "flux_error": "0.18416257", "limiting_flux": "19.959204", "flux_units": "1", "filter_value": "111", "instrument_value": "196", "exptime": "30", "observer": "Robot", "comments": "Data provided by ZTF"}}}, "host_name": "SDSS J080751.29+483812.0"}}}